mec_plugin_cloudify/__init__.py
mec_plugin_cloudify/mec_platform_client.py
mec_plugin_cloudify/tasks.py
mec_plugin_cloudify-0.0.4.dist-info/DESCRIPTION.rst
mec_plugin_cloudify-0.0.4.dist-info/METADATA
mec_plugin_cloudify-0.0.4.dist-info/RECORD
mec_plugin_cloudify-0.0.4.dist-info/WHEEL
mec_plugin_cloudify-0.0.4.dist-info/metadata.json
mec_plugin_cloudify-0.0.4.dist-info/top_level.txt
